edx_django_release_util-1.5.0.dist-info/licenses/LICENSE
release_util/__init__.py
release_util/management/__init__.py
release_util/management/commands/__init__.py
release_util/management/commands/check_reserved_keywords.py
release_util/management/commands/default_reserved_keywords.yml
release_util/management/commands/detect_missing_migrations.py
release_util/management/commands/generate_history.py
release_util/management/commands/run_migrations.py
release_util/management/commands/run_specific_migrations.py
release_util/management/commands/show_unapplied_migrations.py
release_util/tests/migrations/__init__.py
release_util/tests/migrations/test_migrations/0001_initial.py
release_util/tests/migrations/test_migrations/0002_second.py
release_util/tests/migrations/test_migrations/0003_third.py
release_util/tests/migrations/test_migrations/0004_fourth.py
release_util/tests/migrations/test_migrations/__init__.py
release_util/tests/test_check_reserved_keywords/__init__.py
release_util/tests/test_check_reserved_keywords/test_check_reserved_keywords.py
release_util/tests/test_check_reserved_keywords/test_app/__init__.py
release_util/tests/test_check_reserved_keywords/test_app/local_app/__init__.py
release_util/tests/test_check_reserved_keywords/test_app/local_app/apps.py
release_util/tests/test_check_reserved_keywords/test_app/local_app/models.py
release_util/tests/test_check_reserved_keywords/test_app/non_concrete_app/__init__.py
release_util/tests/test_check_reserved_keywords/test_app/non_concrete_app/apps.py
release_util/tests/test_check_reserved_keywords/test_app/non_concrete_app/models.py
release_util/tests/test_check_reserved_keywords/test_app/test_app/__init__.py
release_util/tests/test_check_reserved_keywords/test_app/test_app/settings.py
edx_django_release_util-1.5.0.dist-info/METADATA
edx_django_release_util-1.5.0.dist-info/WHEEL
edx_django_release_util-1.5.0.dist-info/top_level.txt
edx_django_release_util-1.5.0.dist-info/RECORD
